Metadata-Version: 2.1
Name: odoo12-addon-account-payment-return
Version: 12.0.2.1.1
Summary: Manage the return of your payments
Home-page: https://github.com/OCA/account-payment
Author: Odoo Community Association (OCA),7 i TRIA, Tecnativa, initOS GmbH & Co.,
Author-email: support@odoo-community.org
License: AGPL-3
Platform: UNKNOWN
Classifier: Programming Language :: Python
Classifier: Framework :: Odoo
Classifier: License :: OSI Approved :: GNU Affero General Public License v3
Requires-Python: >=3.5
Requires-Dist: odoo (<12.1dev,>=12.0a)
